arikedb_tools/__init__.py
arikedb_tools/command.py
arikedb_tools/events.py
arikedb_tools/exceptions.py
arikedb_tools/sockets.py
arikedb_tools/tables.py
arikedb_tools-1.0.2.dist-info/METADATA
arikedb_tools-1.0.2.dist-info/WHEEL
arikedb_tools-1.0.2.dist-info/top_level.txt
arikedb_tools-1.0.2.dist-info/RECORD
