Metadata-Version: 2.1
Name: arikedb_tools
Version: 1.0.2
Summary: Arikedb Python Tools
Home-page: https://gitlab.com/arikedb1/languages-library-support/tools/arikedb-python-tools
Author: Alejandro Alfonso
Author-email: alejandroalfonso1994@gmail.com
